{
  "main": {
    "id": "81f4d1799608d914",
    "type": "split",
    "children": [
      {
        "id": "c68ab4a999c725a5",
        "type": "tabs",
        "children": [
          {
            "id": "5d919a5a2be7a24c",
            "type": "leaf",
            "state": {
              "type": "markdown",
              "state": {
                "file": "Notes/Javascript/SHORT CIRCUITING.md",
                "mode": "source",
                "source": false
              }
            }
          }
        ]
      }
    ],
    "direction": "vertical"
  },
  "left": {
    "id": "92b8952962b8e2cf",
    "type": "split",
    "children": [
      {
        "id": "3ffab78c05e38196",
        "type": "tabs",
        "children": [
          {
            "id": "226fa247bfcbe2c2",
            "type": "leaf",
            "state": {
              "type": "file-explorer",
              "state": {
                "sortOrder": "alphabetical"
              }
            }
          },
          {
            "id": "dedbbe686b1b6767",
            "type": "leaf",
            "state": {
              "type": "search",
              "state": {
                "query": "",
                "matchingCase": false,
                "explainSearch": false,
                "collapseAll": false,
                "extraContext": false,
                "sortOrder": "alphabetical"
              }
            }
          },
          {
            "id": "2833f2fbc0788f39",
            "type": "leaf",
            "state": {
              "type": "starred",
              "state": {}
            }
          },
          {
            "id": "cd30a1bf7776eef9",
            "type": "leaf",
            "state": {
              "type": "bookmarks",
              "state": {}
            }
          }
        ]
      }
    ],
    "direction": "horizontal",
    "width": 300
  },
  "right": {
    "id": "c9f1c928bd67a3be",
    "type": "split",
    "children": [
      {
        "id": "f78ca79d15e04fd1",
        "type": "tabs",
        "children": [
          {
            "id": "e25155d23e3496c2",
            "type": "leaf",
            "state": {
              "type": "backlink",
              "state": {
                "file": "Notes/Javascript/SHORT CIRCUITING.md",
                "collapseAll": true,
                "extraContext": false,
                "sortOrder": "alphabetical",
                "showSearch": false,
                "searchQuery": "",
                "backlinkCollapsed": false,
                "unlinkedCollapsed": true
              }
            }
          },
          {
            "id": "d2bd08cefb69ef69",
            "type": "leaf",
            "state": {
              "type": "outgoing-link",
              "state": {
                "file": "Notes/Javascript/SHORT CIRCUITING.md",
                "linksCollapsed": false,
                "unlinkedCollapsed": true
              }
            }
          },
          {
            "id": "cbd5606b55d5d730",
            "type": "leaf",
            "state": {
              "type": "tag",
              "state": {
                "sortOrder": "alphabetical",
                "useHierarchy": true
              }
            }
          },
          {
            "id": "7ba5dbfeb040bdeb",
            "type": "leaf",
            "state": {
              "type": "outline",
              "state": {
                "file": "Notes/Javascript/SHORT CIRCUITING.md"
              }
            }
          }
        ],
        "currentTab": 2
      }
    ],
    "direction": "horizontal",
    "width": 300
  },
  "left-ribbon": {
    "hiddenItems": {
      "switcher:Open quick switcher": false,
      "graph:Open graph view": false,
      "canvas:Create new canvas": false,
      "daily-notes:Open today's daily note": false,
      "templates:Insert template": false,
      "command-palette:Open command palette": false
    }
  },
  "active": "5d919a5a2be7a24c",
  "lastOpenFiles": [
    "Notes/Javascript/JAVASCRIPT.md",
    "Notes/Javascript/SHORT CIRCUITING.md",
    "Notes/Javascript/MAPS.md",
    "Notes/Javascript/SETS.md",
    "Notes/Javascript/OPTIONAL CHAINING.md",
    "Notes/Javascript/THIS KEYWORD JS.md",
    "Notes/Javascript/CALL STACK AND HEAP.md",
    "Notes/Javascript/BLOCK AND SHADOWING.md",
    "Notes/Javascript/JS Engine.md",
    "Notes/Javascript/ITERABLES.md",
    "Notes/Javascript/SCOPE , SCOPE CHAIN AND LEXICAL ENVIROMENT.md",
    "Notes/Javascript/OBJECT ORIENTED JS.md",
    "Notes/Javascript/ARRAY JS.md",
    "Notes/Javascript/SHALLOW COPY AND DEEP COPY.md",
    "Notes/Javascript/WEB APIS.md",
    "Notes/Javascript/DOM API.md",
    "Notes/Javascript/STRICT MODE.md",
    "Notes/Javascript/CLOSURE JS.md",
    "Notes/Javascript/TYPEOF OPERATOR JS.md",
    "Notes/Javascript/STATEMENT AND EXPRESSION JS.md",
    "Notes/Javascript/FUNCTION BASIC JS.md",
    "Notes/Javascript/UNDEFINED NULL NaN.md",
    "Notes/Javascript/JavaScript Definition.md",
    "Notes/Javascript/Applying JavaScript to HTML.md",
    "Notes/Javascript/LOOP STATEMENT JS.md",
    "Notes/Javascript/TRUTHY AND FALSY VALUES JS.md",
    "Notes/Assests/Javascript Notes.pdf",
    "New Text Document.txt",
    "Notes/Trading/Options",
    "Untitled",
    "Notes/Trading",
    "Notes/Atomic Habits",
    "Notes/Database",
    "Notes/Assests/HTML/block-element.png",
    "Notes/Assests/HTML/inline-element.png",
    "Notes/Assests/HTML",
    "Notes/Assests/HTML/anatomy-of-element.png",
    "Notes/Assests/HTML",
    "Notes/Assests/Design Guidelines.pdf",
    "Untitled.canvas"
  ]
}